napari_mouse_controls/__init__.py
napari_mouse_controls/_dock_widget.py
napari_mouse_controls/_tests/__init__.py
napari_mouse_controls/_tests/test_dock_widget.py
napari_mouse_controls/icons/Default.png
napari_mouse_controls/icons/Slicing.png
napari_mouse_controls/icons/Windowing.png
napari_mouse_controls/icons/Zoom.png
napari_mouse_controls-0.1.3.dist-info/LICENSE
napari_mouse_controls-0.1.3.dist-info/METADATA
napari_mouse_controls-0.1.3.dist-info/WHEEL
napari_mouse_controls-0.1.3.dist-info/entry_points.txt
napari_mouse_controls-0.1.3.dist-info/top_level.txt
napari_mouse_controls-0.1.3.dist-info/RECORD
