Metadata-Version: 2.1
Name: napari-mouse-controls
Version: 0.1.3
Summary: Control napari using a touch screen
Home-page: https://github.com/haesleinhuepf/napari-mouse-controls
Author: Robert Haase
Author-email: robert.haase@tu-dresden.de
License: BSD-3-Clause
Project-URL: Bug Tracker, https://github.com/haesleinhuepf/napari-mouse-control/issues
Project-URL: Documentation, https://github.com/haesleinhuepf/napari-mouse-controls#README.md
Project-URL: Source Code, https://github.com/haesleinhuepf/napari-mouse-controls
Project-URL: User Support, https://github.com/haesleinhuepf/napari-mouse-controls/issues
Platform: UNKNOWN
Classifier: Development Status :: 2 - Pre-Alpha
Classifier: Intended Audience :: Developers
Classifier: Framework :: napari
Classifier: Programming Language :: Python
Classifier: Programming Language :: Python :: 3
Classifier: Programming Language :: Python :: 3.7
Classifier: Programming Language :: Python :: 3.8
Classifier: Programming Language :: Python :: 3.9
Classifier: Operating System :: OS Independent
Classifier: License :: OSI Approved :: BSD License
Requires-Python: >=3.7
License-File: LICENSE
Requires-Dist: napari-plugin-engine (>=0.1.4)
Requires-Dist: numpy
Requires-Dist: napari
Requires-Dist: napari-tools-menu
